ilinkedlist.py
ilinkedlist-0.4.0.dist-info/DESCRIPTION.rst
ilinkedlist-0.4.0.dist-info/METADATA
ilinkedlist-0.4.0.dist-info/RECORD
ilinkedlist-0.4.0.dist-info/WHEEL
ilinkedlist-0.4.0.dist-info/metadata.json
ilinkedlist-0.4.0.dist-info/top_level.txt
